usermcp/__init__.py
usermcp/profile.py
usermcp/profile_manager.py
usermcp/prompt.py
usermcp-0.1.2.dist-info/licenses/LICENSE
usermcp-0.1.2.dist-info/METADATA
usermcp-0.1.2.dist-info/WHEEL
usermcp-0.1.2.dist-info/top_level.txt
usermcp-0.1.2.dist-info/RECORD
