Metadata-Version: 2.4
Name: usermcp
Version: 0.1.2
Summary: Add your description here
License: MIT
Keywords: mcp,agent,llm,profile,user
Classifier: Intended Audience :: Developers
Classifier: Operating System :: OS Independent
Classifier: Programming Language :: Python :: 3
Requires-Python: >=3.10
License-File: LICENSE
Requires-Dist: mcp[cli]>=1.12.3
Requires-Dist: pyyaml>=6.0.2
Dynamic: license-file
